baxiapi/__init__ 2.py
baxiapi/__init__.py
baxiapi-2.2.1.dist-info/METADATA
baxiapi-2.2.1.dist-info/WHEEL
baxiapi-2.2.1.dist-info/top_level.txt
baxiapi-2.2.1.dist-info/RECORD
