Metadata-Version: 2.1
Name: baxiapi
Version: 2.2.1
Summary: Allows you to interact with our Baxi API.
Author: Red_Wolf2467
Author-email: support@pyropixle.com
Requires-Python: >=3.8
Requires-Dist: requests
Requires-Dist: wavelink
Requires-Dist: discord.py
Requires-Dist: reds-simple-logger
